<level>
  <type>section</type>
  <num>6-116.1</num>
  <heading>Information required to be kept on contractor performance.</heading>
  <text>ยง 6-116.1 Information required to be kept on contractor performance. All agencies letting contracts shall monitor the performance of every contractor. Information with respect to contractor performance shall be maintained by the city at a central location
    and shall be accessible to the members of the board of estimate, the members of the city council and city agencies upon request.</text>
</level>