<level>
  <type>section</type>
  <num>24-146.2</num>
  <heading>Enforcement of the labor law.</heading>
  <text>ยง 24-146.2 Enforcement of the labor law. Pursuant to subdivision two of section nine hundred ten of the labor law, the commissioner shall have all the powers and responsibility of the commissioner of labor in enforcing the provisions of article thirty
    of the labor law and the rules and regulations adopted thereunder; provided, however, that the civil penalties authorized pursuant to subdivisions one and two of section nine hundred nine of such law shall be imposed by the environmental control board
    after a hearing in accordance with the rules of the board.</text>
</level>